fundrive/__init__.py
fundrive/core/__init__.py
fundrive/core/base.py
fundrive/core/constants.py
fundrive/core/copy.py
fundrive/core/exceptions.py
fundrive/core/snapshot.py
fundrive/core/test.py
fundrive/core/utils.py
fundrive/drives/__init__.py
fundrive/drives/alipan/__init__.py
fundrive/drives/alipan/drive_aligo.py
fundrive/drives/alipan/drive_open.py
fundrive/drives/alipan/example.py
fundrive/drives/amazon/__init__.py
fundrive/drives/amazon/drive.py
fundrive/drives/amazon/example.py
fundrive/drives/baidu/__init__.py
fundrive/drives/baidu/drive.py
fundrive/drives/baidu/example.py
fundrive/drives/dropbox/__init__.py
fundrive/drives/dropbox/drive.py
fundrive/drives/dropbox/example.py
fundrive/drives/gitee/__init__.py
fundrive/drives/gitee/drive.py
fundrive/drives/gitee/example.py
fundrive/drives/github/__init__.py
fundrive/drives/github/drive.py
fundrive/drives/github/example.py
fundrive/drives/google/__init__.py
fundrive/drives/google/drive.py
fundrive/drives/google/example.py
fundrive/drives/lanzou/__init__.py
fundrive/drives/lanzou/drive.py
fundrive/drives/lanzou/example.py
fundrive/drives/lanzou/snapshot.py
fundrive/drives/mediafire/__init__.py
fundrive/drives/mediafire/drive.py
fundrive/drives/mediafire/example.py
fundrive/drives/onedrive/__init__.py
fundrive/drives/onedrive/drive.py
fundrive/drives/onedrive/example.py
fundrive/drives/openxlab/__init__.py
fundrive/drives/openxlab/drive.py
fundrive/drives/openxlab/example.py
fundrive/drives/os/__init__.py
fundrive/drives/os/drive.py
fundrive/drives/os/example.py
fundrive/drives/oss/__init__.py
fundrive/drives/oss/drive.py
fundrive/drives/oss/example.py
fundrive/drives/ossutil/__init__.py
fundrive/drives/ossutil/drive.py
fundrive/drives/ossutil/example.py
fundrive/drives/pcloud/__init__.py
fundrive/drives/pcloud/drive.py
fundrive/drives/pcloud/example.py
fundrive/drives/tianchi/__init__.py
fundrive/drives/tianchi/drive.py
fundrive/drives/tianchi/example.py
fundrive/drives/tsinghua/__init__.py
fundrive-2.0.53.dist-info/METADATA
fundrive-2.0.53.dist-info/WHEEL
fundrive-2.0.53.dist-info/top_level.txt
fundrive-2.0.53.dist-info/RECORD
