Metadata-Version: 2.4
Name: fundrive
Version: 2.0.53
Summary: fundrive
Author-email: 牛哥 <niuliangtao@qq.com>, farfarfun <farfarfun@qq.com>
Maintainer-email: 牛哥 <niuliangtao@qq.com>, farfarfun <farfarfun@qq.com>
Project-URL: Organization, https://github.com/farfarfun
Project-URL: Repository, https://github.com/farfarfun/fundrive
Project-URL: Releases, https://github.com/farfarfun/fundrive/releases
Requires-Python: >=3.8
Requires-Dist: funget>=1.0.34
Requires-Dist: funsecret>=1.4.49
Requires-Dist: orjson>=3.10.10
Requires-Dist: requests>=2.32.4
Requires-Dist: tqdm>=4.67.1
Provides-Extra: alipan
Requires-Dist: aligo>=6.2.4; extra == "alipan"
Requires-Dist: fundrive-alipan; extra == "alipan"
Provides-Extra: oss
Requires-Dist: oss2>=2.19.0; extra == "oss"
Provides-Extra: webdav
Requires-Dist: webdav4>=0.10.0; extra == "webdav"
Provides-Extra: wenshushu
Requires-Dist: base58>=2.1.1; extra == "wenshushu"
Requires-Dist: pycryptodomex>=3.21.0; extra == "wenshushu"
Provides-Extra: baidu
Requires-Dist: fundrive-baidu; extra == "baidu"
Provides-Extra: lanzou
Requires-Dist: fundrive-lanzou; extra == "lanzou"
Provides-Extra: plcoud
Requires-Dist: requests; extra == "plcoud"
Provides-Extra: dropbox
Requires-Dist: dropbox>=12.0.2; extra == "dropbox"
Provides-Extra: google
Requires-Dist: google-api-python-client>=2.0.0; extra == "google"
Requires-Dist: google-auth-httplib2>=0.1.0; extra == "google"
Requires-Dist: google-auth-oauthlib>=1.0.0; extra == "google"
Provides-Extra: onedrive
Requires-Dist: requests>=2.25.0; extra == "onedrive"
Provides-Extra: amazon
Requires-Dist: boto3>=1.34.0; extra == "amazon"
Provides-Extra: tsinghua
Requires-Dist: requests>=2.32.4; extra == "tsinghua"
Provides-Extra: github
Requires-Dist: requests>=2.32.4; extra == "github"
Requires-Dist: orjson>=3.10.10; extra == "github"
Provides-Extra: gitee
Requires-Dist: requests>=2.32.4; extra == "gitee"
Requires-Dist: orjson>=3.10.10; extra == "gitee"
Provides-Extra: ossutil
Requires-Dist: funinstall>=1.0.58; extra == "ossutil"
